asreviewcontrib/hyperopt/__init__.py
asreviewcontrib/hyperopt/active.py
asreviewcontrib/hyperopt/active_job.py
asreviewcontrib/hyperopt/cluster.py
asreviewcontrib/hyperopt/cluster_job.py
asreviewcontrib/hyperopt/cluster_utils.py
asreviewcontrib/hyperopt/create_config.py
asreviewcontrib/hyperopt/job_utils.py
asreviewcontrib/hyperopt/mpi_executor.py
asreviewcontrib/hyperopt/passive.py
asreviewcontrib/hyperopt/passive_job.py
asreviewcontrib/hyperopt/serial_executor.py
asreviewcontrib/hyperopt/show_trials.py
asreview_hyperopt-0.2.0.dist-info/LICENSE
asreview_hyperopt-0.2.0.dist-info/METADATA
asreview_hyperopt-0.2.0.dist-info/WHEEL
asreview_hyperopt-0.2.0.dist-info/entry_points.txt
asreview_hyperopt-0.2.0.dist-info/top_level.txt
asreview_hyperopt-0.2.0.dist-info/RECORD
