Metadata-Version: 2.1
Name: asreview-hyperopt
Version: 0.2.0
Summary: Hyper parameter optimization extension for ASReview
Home-page: https://github.com/asreview/asreview-hyperopt
Author: Utrecht University
Author-email: asreview@uu.nl
License: UNKNOWN
Project-URL: Bug Reports, https://github.com/asreview/asreview-hyperopt/issues
Project-URL: Source, https://github.com/asreview/asreview-hyperopt
Keywords: asreview plot hyperopt optimization
Platform: UNKNOWN
Classifier: Development Status :: 3 - Alpha
Classifier: License :: OSI Approved :: Apache Software License
Classifier: Programming Language :: Python :: 3.5
Classifier: Programming Language :: Python :: 3.6
Classifier: Programming Language :: Python :: 3.7
Requires-Dist: asreview (>=0.7.0)
Requires-Dist: numpy
Requires-Dist: tqdm
Requires-Dist: hyperopt
Requires-Dist: sklearn
Provides-Extra: all
Requires-Dist: mpi4py ; extra == 'all'
Provides-Extra: mpi
Requires-Dist: mpi4py ; extra == 'mpi'
